fdet_offline_mtcnn_weights/__init__.py
fdet_offline_mtcnn_weights/import_weights.py
fdet_offline_mtcnn_weights/weights/__init__.py
fdet_offline_mtcnn_weights/weights/get_path.py
fdet_offline_mtcnn_weights/weights/mtcnn_onet.pt
fdet_offline_mtcnn_weights/weights/mtcnn_pnet.pt
fdet_offline_mtcnn_weights/weights/mtcnn_rnet.pt
fdet_offline_mtcnn_weights-1.0.0.dist-info/LICENSE.txt
fdet_offline_mtcnn_weights-1.0.0.dist-info/METADATA
fdet_offline_mtcnn_weights-1.0.0.dist-info/WHEEL
fdet_offline_mtcnn_weights-1.0.0.dist-info/top_level.txt
fdet_offline_mtcnn_weights-1.0.0.dist-info/RECORD
