Metadata-Version: 2.1
Name: fdet-offline-mtcnn-weights
Version: 1.0.0
Summary: Weights for the models in fdet-offline.
Home-page: https://github.com/vikrosj/fdet-offline-mtcnn-weights
Author: Viktoria R.
Author-email: viktoria.rosjo@gmail.com
Maintainer: Viktoria R.
Maintainer-email: viktoria.rosjo@gmail.com
License: UNKNOWN
Download-URL: https://github.com/vikrosj/fdet-offline-mtcnn-weights/archive/1.0.0.tar.gz
Keywords: face recognition detection biometry
Platform: UNKNOWN
Requires-Python: >=3.5
Requires-Dist: future (==0.18.2)
Requires-Dist: numpy (==1.19.2)
Requires-Dist: torch (==1.6.0)
